maitai/__init__.py
maitai/_config.py
maitai/_eval_request.py
maitai/_evaluator.py
maitai/_loadable.py
maitai/_maitai_object.py
maitai/config.py
maitai_sdk_python-0.424.dist-info/METADATA
maitai_sdk_python-0.424.dist-info/WHEEL
maitai_sdk_python-0.424.dist-info/top_level.txt
maitai_sdk_python-0.424.dist-info/RECORD
