Metadata-Version: 2.1
Name: maitai-sdk-python
Version: 0.424
Summary: MaiTai SDK for Python
Home-page: https://github.com/yewpay/maitai-sdk-python
Author: Christian DalSanto
Author-email: christian@yewpay.com
License: MIT
Classifier: Programming Language :: Python :: 3
Classifier: License :: OSI Approved :: MIT License
Requires-Dist: requests
Requires-Dist: aiohttp
